{
  "appId": "com.guardian.erp.mobile",
  "appName": "Guardian ERP",
  "webDir": "dist",
  "server": {
    "androidScheme": "https",
    "cleartext": false
  },
  "plugins": {
    "SplashScreen": {
      "launchShowDuration": 2000,
      "launchAutoHide": true,
      "backgroundColor": "#0f172a",
      "androidSplashResourceName": "splash",
      "iosSplashResourceName": "Splash",
      "showSpinner": true,
      "spinnerStyle": "large",
      "spinnerColor": "#0d9488"
    },
    "Keyboard": {
      "resize": "native",
      "resizeOnFullScreen": true
    },
    "StatusBar": {
      "style": "dark",
      "backgroundColor": "#0f172a"
    },
    "PushNotifications": {
      "presentationOptions": ["badge", "sound", "alert"]
    },
    "LocalNotifications": {
      "smallIcon": "ic_stat_icon",
      "iconColor": "#0d9488"
    },
    "App": {
      "launchUrl": "index.html"
    }
  },
  "android": {
    "allowMixedContent": false,
    "captureInput": true,
    "webContentsDebuggingEnabled": false,
    "backgroundColor": "#0f172a",
    "buildOptions": {
      "signingType": "apksigner"
    }
  },
  "ios": {
    "contentInset": "automatic",
    "preferredContentMode": "mobile",
    "limitsNavigationsToAppBoundDomains": true
  }
}
